latools/D_obj.py
latools/__init__.py
latools/dev.ipynb
latools/dev_dspk.ipynb
latools/latools.cfg
latools/latools.py
latools/latools_graveyard.py
latools/tags.QLUftn
latools/filtering/__init__.py
latools/filtering/classifier_obj.py
latools/filtering/clustering.py
latools/filtering/filt_obj.py
latools/filtering/filters.py
latools/filtering/pca.py
latools/filtering/signal_optimiser.py
latools/helpers/__init__.py
latools/helpers/analyte_names.py
latools/helpers/analytes.py
latools/helpers/chemistry.py
latools/helpers/config.py
latools/helpers/helpers.py
latools/helpers/io.py
latools/helpers/logging.py
latools/helpers/metadata_parsers.py
latools/helpers/plot.py
latools/helpers/progressbars.py
latools/helpers/signal.py
latools/helpers/srm.py
latools/helpers/stat_fns.py
latools/helpers/utils.py
latools/mapping/__init__.py
latools/mapping/io.py
latools/mapping/plot.py
latools/preprocessing/__init__.py
latools/preprocessing/split.py
latools/processes/__init__.py
latools/processes/data_read.py
latools/processes/despiking.py
latools/processes/signal_id.py
latools/resources/SRM_GeoRem_Preferred_170622.csv
latools/resources/SRM_GeoRem_Preferred_170622_backup.csv
latools/resources/SRM_ratios_160713.csv
latools/resources/elements.pkl
latools/resources/data_formats/ANU_iCAP-RQ.json
latools/resources/data_formats/Brest_NuAtom_dataformat.json
latools/resources/data_formats/CAM-iCap-long.json
latools/resources/data_formats/CAM-iCap.json
latools/resources/data_formats/GEOMAR-Atom.json
latools/resources/data_formats/GEOMAR-FIN2.json
latools/resources/data_formats/UCD_dataformat.dict
latools/resources/data_formats/UCD_dataformat.json
latools/resources/data_formats/USC_Element_dataformat.dict
latools/resources/data_formats/dataformat_template.json
latools/resources/data_formats/repro_dataformat.dict
latools/resources/data_formats/repro_dataformat.json
latools/resources/test_data/STD-1.csv
latools/resources/test_data/STD-2.csv
latools/resources/test_data/Sample-1.csv
latools-0.3.31.dist-info/LICENCE.txt
latools-0.3.31.dist-info/METADATA
latools-0.3.31.dist-info/WHEEL
latools-0.3.31.dist-info/top_level.txt
latools-0.3.31.dist-info/RECORD
