Metadata-Version: 2.1
Name: latools
Version: 0.3.31
Summary: Tools for LA-ICPMS data analysis.
Home-page: https://github.com/oscarbranson/latools
Author: Oscar Branson
Author-email: ob266@cam.ac.uk
License: MIT
Project-URL: PalaeoCarb Project, https://github.com/PalaeoCarb
Classifier: Programming Language :: Python :: 3
Classifier: Intended Audience :: Science/Research
Classifier: Topic :: Scientific/Engineering
Classifier: Programming Language :: Python :: 3
Requires-Python: >3.6
License-File: LICENCE.txt
Requires-Dist: numpy
Requires-Dist: pandas
Requires-Dist: matplotlib
Requires-Dist: uncertainties
Requires-Dist: scikit-learn
Requires-Dist: scipy
Requires-Dist: Ipython
Requires-Dist: setuptools
